cognite_synthetic_tags/__init__.py
cognite_synthetic_tags/_operations.py
cognite_synthetic_tags/data_stores.py
cognite_synthetic_tags/tag.py
cognite_synthetic_tags/tag_resolver.py
cognite_synthetic_tags/types.py
cognite_synthetic_tags-0.5.2.dist-info/METADATA
cognite_synthetic_tags-0.5.2.dist-info/WHEEL
cognite_synthetic_tags-0.5.2.dist-info/RECORD
